tkinter_yzw/__init__.py
tkinter_yzw/tk_autoscrollbar.py
tkinter_yzw/tk_dialog.py
tkinter_yzw/tk_index.py
tkinter_yzw/tk_listedit.py
tkinter_yzw/tk_listview.py
tkinter_yzw/tk_mainui.py
tkinter_yzw/tk_pages.py
tkinter_yzw/tk_sheet.py
tkinter_yzw/tk_sizer.py
tkinter_yzw/tk_table.py
tkinter_yzw/tk_text.py
tkinter_yzw/tk_tooltip.py
tkinter_yzw/tk_tree.py
tkinter_yzw-0.1.dist-info/LICENSE
tkinter_yzw-0.1.dist-info/METADATA
tkinter_yzw-0.1.dist-info/WHEEL
tkinter_yzw-0.1.dist-info/top_level.txt
tkinter_yzw-0.1.dist-info/RECORD
